Products
setup.py
Products/RadioSchedule
Products/__init__.py
Products.RadioSchedule.egg-info/PKG-INFO
Products.RadioSchedule.egg-info/SOURCES.txt
Products.RadioSchedule.egg-info/SOURCES.txt~
Products.RadioSchedule.egg-info/dependency_links.txt
Products.RadioSchedule.egg-info/entry_points.txt
Products.RadioSchedule.egg-info/namespace_packages.txt
Products.RadioSchedule.egg-info/not-zip-safe
Products.RadioSchedule.egg-info/requires.txt
Products.RadioSchedule.egg-info/top_level.txt
Products/RadioSchedule/__init__.py
Products/RadioSchedule/_darcs
Products/RadioSchedule/changes.txt
Products/RadioSchedule/config.py
Products/RadioSchedule/configure.zcml
Products/RadioSchedule/contents
Products/RadioSchedule/i18n
Products/RadioSchedule/locales
Products/RadioSchedule/profiles
Products/RadioSchedule/profiles.zcml
Products/RadioSchedule/readme.txt
Products/RadioSchedule/refresh.txt
Products/RadioSchedule/setuphandlers.py
Products/RadioSchedule/skins
Products/RadioSchedule/validators.py
Products/RadioSchedule/_darcs/format
Products/RadioSchedule/_darcs/hashed_inventory
Products/RadioSchedule/_darcs/index_invalid
Products/RadioSchedule/_darcs/inventories
Products/RadioSchedule/_darcs/patches
Products/RadioSchedule/_darcs/prefs
Products/RadioSchedule/_darcs/pristine.hashed
Products/RadioSchedule/_darcs/tentative_pristine
Products/RadioSchedule/_darcs/inventories/0000000186-fcc4160d490e4954ff14640a4c1d7921c653ed0680f4b79e0473c12c94d8f43f
Products/RadioSchedule/_darcs/inventories/0000000471-7f0bc9d6274ed6d870599019002ce5665a8e1f3b0076531bddee0bb0a51475dd
Products/RadioSchedule/_darcs/patches/0000000898-65aa671f1d2926da9636efdd6998e97dc9ed73d738f611eb27ae93d3a0da1732
Products/RadioSchedule/_darcs/patches/0000054473-709a5a2a0400099d5163197c7f44cb44ad73670ae91fbe969134b5e8d8f280b4
Products/RadioSchedule/_darcs/patches/pending
Products/RadioSchedule/_darcs/patches/pending.tentative
Products/RadioSchedule/_darcs/prefs/author
Products/RadioSchedule/_darcs/prefs/binaries
Products/RadioSchedule/_darcs/prefs/boring
Products/RadioSchedule/_darcs/prefs/motd
Products/RadioSchedule/_darcs/pristine.hashed/0000000000-e3b0c44298fc1c149afbf4c8996fb92427ae41e4649b934ca495991b7852b855
Products/RadioSchedule/_darcs/pristine.hashed/0000000072-620bbc5e8a995b216008b582dcddad5285898340c288338311b52b32ea65dc62
