Metadata-Version: 1.0
Name: Products.RadioSchedule
Version: 1.0a
Summary: A content-type for storing information about radio show sending schedules
Home-page: http://www.nidelven-it.no/d
Author: Nidelven IT (Stig Rune Oeyra)
Author-email: info@nidelven-it.no
License: GPL
Keywords: python plone content
Platform: UNKNOWN
Classifier: Programming Language :: Python
Classifier: Framework :: Plone
